Metadata-Version: 2.1
Name: metabase-import-export
Version: 0.2.2
Summary: Export/Import Metabase collections to JSON files.
Home-page: UNKNOWN
License: BSD 3-Clause License
Keywords: metabase
Platform: UNKNOWN
Classifier: License :: OSI Approved :: BSD License
Classifier: Programming Language :: Python :: 3
